acentoweb.collectionactions-1.0a1-py2.7-nspkg.pth
acentoweb/.DS_Store
acentoweb/collectionactions/.DS_Store
acentoweb/collectionactions/__init__.py
acentoweb/collectionactions/configure.zcml
acentoweb/collectionactions/interfaces.py
acentoweb/collectionactions/permissions.zcml
acentoweb/collectionactions/setuphandlers.py
acentoweb/collectionactions/testing.py
acentoweb/collectionactions/behaviors/__init__.py
acentoweb/collectionactions/behaviors/collection_copy.py
acentoweb/collectionactions/behaviors/collection_move.py
acentoweb/collectionactions/behaviors/configure.zcml
acentoweb/collectionactions/behaviors/configure.zcml.example
acentoweb/collectionactions/browser/__init__.py
acentoweb/collectionactions/browser/actions.py
acentoweb/collectionactions/browser/configure.zcml
acentoweb/collectionactions/browser/overrides/.gitkeep
acentoweb/collectionactions/browser/static/.gitkeep
acentoweb/collectionactions/locales/README.rst
acentoweb/collectionactions/locales/__init__.py
acentoweb/collectionactions/locales/acentoweb.collectionactions.pot
acentoweb/collectionactions/locales/update.py
acentoweb/collectionactions/locales/update.sh
acentoweb/collectionactions/locales/en/LC_MESSAGES/acentoweb.collectionactions.mo
acentoweb/collectionactions/locales/en/LC_MESSAGES/acentoweb.collectionactions.po
acentoweb/collectionactions/profiles/.DS_Store
acentoweb/collectionactions/profiles/default/actions.xml
acentoweb/collectionactions/profiles/default/browserlayer.xml
acentoweb/collectionactions/profiles/default/catalog.xml
acentoweb/collectionactions/profiles/default/metadata.xml
acentoweb/collectionactions/profiles/default/registry.xml
acentoweb/collectionactions/profiles/default/rolemap.xml
acentoweb/collectionactions/profiles/uninstall/actions.xml
acentoweb/collectionactions/profiles/uninstall/browserlayer.xml
acentoweb/collectionactions/tests/__init__.py
acentoweb/collectionactions/tests/test_behavior_collection_copy.py
acentoweb.collectionactions-1.0a1.dist-info/METADATA
acentoweb.collectionactions-1.0a1.dist-info/RECORD
acentoweb.collectionactions-1.0a1.dist-info/WHEEL
acentoweb.collectionactions-1.0a1.dist-info/entry_points.txt
acentoweb.collectionactions-1.0a1.dist-info/namespace_packages.txt
acentoweb.collectionactions-1.0a1.dist-info/top_level.txt
